pyqulator/__init__.py
pyqulator/main.py
pyqulator/ui.py
pyqulator/locales/ui_ru.qm
pyqulator/locales/ui_uk.qm
pyqulator-1.13.0.dist-info/LICENSE
pyqulator-1.13.0.dist-info/METADATA
pyqulator-1.13.0.dist-info/WHEEL
pyqulator-1.13.0.dist-info/entry_points.txt
pyqulator-1.13.0.dist-info/top_level.txt
pyqulator-1.13.0.dist-info/RECORD
