Metadata-Version: 2.1
Name: pyqulator
Version: 1.13.0
Summary: A fully functional Qt calculator written in Python using Sympy for calculations
Author-email: limafresh <limafresh@proton.me>
License: GNU GENERAL PUBLIC LICENSE
Project-URL: Repository, https://github.com/limafresh/pyqulator
Project-URL: Issues, https://github.com/limafresh/pyqulator/issues
Keywords: calculator,project,pyqt,pyqt6,pyqt-calculator,sympy,pip,gui-project
Classifier: Development Status :: 5 - Production/Stable
Classifier: License :: OSI Approved :: GNU General Public License v3 (GPLv3)
Classifier: Programming Language :: Python :: 3
Classifier: Operating System :: OS Independent
Classifier: Intended Audience :: End Users/Desktop
Classifier: Environment :: X11 Applications :: Qt
Classifier: Topic :: Scientific/Engineering :: Mathematics
Classifier: Natural Language :: Ukrainian
Classifier: Natural Language :: Russian
Classifier: Natural Language :: English
Classifier: Topic :: Utilities
Requires-Python: >=3.8
License-File: LICENSE
Requires-Dist: PyQt6>=6.4.2
Requires-Dist: sympy>=1.13.3
